aldryn_common/__init__.py
aldryn_common/compat.py
aldryn_common/paginator.py
aldryn_common/slugs.py
aldryn_common/timesince.py
aldryn_common/tools.py
aldryn_common/admin_fields/__init__.py
aldryn_common/admin_fields/sortedm2m.py
aldryn_common/boilerplates/bootstrap3/templates/aldryn_common/paginator.html
aldryn_common/boilerplates/legacy/templates/aldryn_common/paginator.html
aldryn_common/templates/admin/aldryn_common/widgets/sortedm2m_widget.html
aldryn_common/templatetags/__init__.py
aldryn_common/templatetags/date_range.py
aldryn_common/templatetags/html_filter_tags.py
aldryn_common/templatetags/query_string_tools.py
aldryn_common/templatetags/string_tags.py
aldryn_common-1.0.3.dist-info/DESCRIPTION.rst
aldryn_common-1.0.3.dist-info/METADATA
aldryn_common-1.0.3.dist-info/RECORD
aldryn_common-1.0.3.dist-info/WHEEL
aldryn_common-1.0.3.dist-info/metadata.json
aldryn_common-1.0.3.dist-info/top_level.txt
tests/__init__.py
tests/test_templatetags.py
