Metadata-Version: 2.0
Name: aldryn-common
Version: 1.0.3
Summary: Common utitilities
Home-page: https://github.com/aldryn/aldryn-common
Author: Divio AG
Author-email: info@divio.ch
License: LICENSE.txt
Platform: OS Independent
Classifier: Development Status :: 5 - Production/Stable
Classifier: Environment :: Web Environment
Classifier: Framework :: Django
Classifier: Intended Audience :: Developers
Classifier: License :: OSI Approved :: BSD License
Classifier: Operating System :: OS Independent
Classifier: Programming Language :: Python
Classifier: Topic :: Internet :: WWW/HTTP :: Dynamic Content
Classifier: Topic :: Software Development
Classifier: Topic :: Software Development :: Libraries :: Application Frameworks
Classifier: Programming Language :: Python :: 2.7
Classifier: Programming Language :: Python :: 3.3
Classifier: Programming Language :: Python :: 3.4
Classifier: Programming Language :: Python :: 3.5
Requires-Dist: aldryn-boilerplates
Requires-Dist: django-sortedm2m (>=1.2.2,<1.3)
Requires-Dist: six
